{
  "config": {
    "chainId": 648629,
    "byzantiumBlock": 0,
    "ibft2": {
      "blockperiodseconds": 2,
      "epochlength": 30000,
      "requesttimeoutseconds": 4,
      "blockreward": "5000000000000000",
      "miningbeneficiary": "0xF889c7F330F803161830EAd634f0d7Da708cb199"
    },
    "transitions" : {
      "ibft2" : [
      {
        "block": 40,
        "miningbeneficiary": "0x49C90a296e3f86FfCf1115528932a3e62Aae0597"
      }
      ]
    }

  },
  "nonce": "0x0",
  "timestamp": "0x58ee40ba",
  "extraData": "<definir extraData>",
  "gasLimit": "0x1fffffffffffff",
  "difficulty": "0x1",
  "coinbase": "0x0000000000000000000000000000000000000000",
  "mixHash": "0x63746963616c2062797a616e74696e65206661756c7420746f6c6572616e6365",
  "alloc": {
    "9811ebc35d7b06b3fa8dc5809a1f9c52751e1deb": {
      "balance": "0xad78ebc5ac6200000"
    }
  }
}
